setup.py
schemato/__init__.py
schemato/compound_graph.py
schemato/distillers.py
schemato/distillery.py
schemato/errors.py
schemato/schemadef.py
schemato/schemato.py
schemato/settings.py
schemato/test.py
schemato/utils.py
schemato/validationresult.py
schemato/validator.py
schemato.egg-info/PKG-INFO
schemato.egg-info/SOURCES.txt
schemato.egg-info/dependency_links.txt
schemato.egg-info/entry_points.txt
schemato.egg-info/requires.txt
schemato.egg-info/top_level.txt
schemato/schemas/__init__.py
schemato/schemas/opengraph.py
schemato/schemas/parselypage.py
schemato/schemas/rnews.py
schemato/schemas/schemaorg.py
schemato/schemas/schemaorg_rdf.py