Metadata-Version: 1.1
Name: schemato
Version: 1.3.0
Summary: Unified semantic metadata validator
Home-page: https://github.com/Parsely/schemato
Author: Emmett Butler
Author-email: emmett@parsely.com
License: UNKNOWN
Keywords: microdata rdf metadata
Platform: any
Classifier: Development Status :: 3 - Alpha
Classifier: Intended Audience :: Developers
Classifier: Operating System :: OS Independent
Classifier: Programming Language :: Python
